LICENSE
README.md
async_sendgrid/__init__.py
async_sendgrid/exception.py
async_sendgrid/pool.py
async_sendgrid/sendgrid.py
async_sendgrid/telemetry.py
sendgrid_async-2.1.1.dist-info/LICENSE
sendgrid_async-2.1.1.dist-info/METADATA
sendgrid_async-2.1.1.dist-info/WHEEL
sendgrid_async-2.1.1.dist-info/RECORD
