Metadata-Version: 2.1
Name: sendgrid-async
Version: 2.1.1
Summary: SendGrid using an httpx client
Home-page: https://github.com/EM51641/async-sendgrid-
License: MIT
Keywords: sendgrid,client,async
Author: Elyes Mahjoubi
Author-email: elyesmahjoubi@gmail.com
Requires-Python: >=3.10,<4.0
Classifier: License :: OSI Approved :: MIT License
Classifier: Operating System :: OS Independent
Classifier: Programming Language :: Python :: 3
Classifier: Programming Language :: Python :: 3.10
Classifier: Programming Language :: Python :: 3.11
Classifier: Programming Language :: Python :: 3.10
Classifier: Programming Language :: Python :: 3.11
Classifier: Programming Language :: Python :: 3.12
Classifier: Programming Language :: Python :: 3.13
Requires-Dist: httpx (>=0.24.1,<0.29.0)
Requires-Dist: opentelemetry-api (>=1.34.0,<2.0.0)
Requires-Dist: opentelemetry-exporter-otlp-proto-grpc (>=1.34.0,<2.0.0)
Requires-Dist: opentelemetry-sdk (>=1.34.0,<2.0.0)
Requires-Dist: sendgrid (>=6.7.0,<7.0.0)
Project-URL: Repository, https://github.com/EM51641/async-sendgrid-
